<?xml version="1.0" encoding="UTF-8"?>
<manifest xmlns:android="http://schemas.android.com/apk/res/android">

	<permissionConfig>
    <uses-permission android:name="android.permission.ACCESS_NETWORK_STATE" />
    <uses-permission android:name="android.permission.ACCESS_WIFI_STATE" />
    <uses-permission android:name="android.permission.INTERNET" />
    <uses-permission android:name="android.permission.READ_PHONE_STATE" />
    <uses-permission android:name="android.permission.READ_LOGS" />
    <uses-permission android:name="android.permission.ACCESS_COARSE_LOCATION" />
    <uses-permission android:name="android.permission.ACCESS_WIFI_STATE" />
    <uses-permission android:name="android.permission.WRITE_EXTERNAL_STORAGE" />
    <uses-permission android:name="android.permission.CALL_PHONE" />
    <uses-permission android:name="org.simalliance.openmobileapi.SMARTCARD" />
    <uses-permission android:name="android.permission.NFC" />
    <uses-feature android:name="android.hardware.nfc.hce" />
    <uses-permission android:name="android.permission.READ_SMS" />
    <uses-permission android:name="android.permission.ACCESS_FINE_LOCATION" />
    <uses-permission android:name="android.permission.WRITE_SETTINGS" />
    <uses-permission android:name="android.permission.READ_SETTINGS" />
    <uses-permission android:name="android.permission.MOUNT_UNMOUNT_FILESYSTEMS" />
    <uses-permission android:name="android.permission.GET_TASKS" />
    <uses-permission android:name="com.alipay.mobile.command.trigger.permission" />
    <uses-permission android:name="android.permission.VIBRATE" />
    <uses-permission android:name="android.permission.RECEIVE_SMS" />
    <uses-permission android:name="android.webkit.permission.PLUGIN" />
    <uses-permission android:name="android.permission.CHANGE_NETWORK_STATE" />
	</permissionConfig>

	<applicationConfig>
     <activity
            android:name="com.pptv.vassdk.ui.activity.login.OneKeyRegistActivity"
            android:screenOrientation="behind"
            android:theme="@android:style/Theme.Translucent.NoTitleBar.Fullscreen" />
        <activity
            android:name="com.pptv.vassdk.ui.activity.login.FirstLoginActivity"
            android:screenOrientation="behind"
            android:theme="@android:style/Theme.Translucent.NoTitleBar.Fullscreen" />
        <activity
            android:name="com.pptv.vassdk.ui.activity.login.function.ForgetPassword"
            android:screenOrientation="behind"
            android:theme="@android:style/Theme.Translucent.NoTitleBar.Fullscreen" />
        <activity
            android:name="com.pptv.vassdk.ui.activity.login.LoginRegisterActivity"
            android:screenOrientation="behind"
            android:theme="@android:style/Theme.Translucent.NoTitleBar.Fullscreen" />
        <activity
            android:name="com.pptv.vassdk.ui.activity.login.AutoLoginActivity"
            android:screenOrientation="behind"
            android:theme="@android:style/Theme.Translucent.NoTitleBar.Fullscreen" />
        <activity
            android:name="com.pptv.vassdk.ui.activity.welcome.WelcomePageActivity"
            android:screenOrientation="behind"
            android:configChanges="orientation|keyboard|keyboardHidden|screenSize"
            android:theme="@android:style/Theme.Translucent.NoTitleBar.Fullscreen" />
        <activity
            android:name="com.pptv.vassdk.ui.activity.welcome.AccountSettingsActivity"
            android:screenOrientation="behind"
            android:theme="@android:style/Theme.Translucent.NoTitleBar.Fullscreen" />
        <activity
            android:name="com.pptv.vassdk.ui.activity.welcome.UnbindPhoneActivity"
            android:screenOrientation="behind"
            android:theme="@android:style/Theme.Translucent.NoTitleBar.Fullscreen" />
        <activity
            android:name="com.pptv.vassdk.ui.activity.welcome.GiftActivity"
            android:screenOrientation="behind"
            android:theme="@android:style/Theme.Translucent.NoTitleBar.Fullscreen" />
        <activity
            android:name="com.pptv.vassdk.ui.activity.welcome.ModifyPassWordActivity"
            android:screenOrientation="behind"
            android:theme="@android:style/Theme.Translucent.NoTitleBar.Fullscreen" />
        <activity
            android:name="com.pptv.vassdk.ui.activity.welcome.GiftUsageGuideActivity"
            android:screenOrientation="behind"
            android:theme="@android:style/Theme.Translucent.NoTitleBar.Fullscreen" />
        <activity
            android:name="com.pptv.vassdk.ui.activity.welcome.ChargeRecordActivity"
            android:screenOrientation="behind"
            android:theme="@android:style/Theme.Translucent.NoTitleBar.Fullscreen" />
        <activity
            android:name="com.pptv.vassdk.ui.activity.login.function.BindPhoneActivity"
            android:screenOrientation="behind"
            android:theme="@android:style/Theme.Translucent.NoTitleBar.Fullscreen" />
        <activity
            android:name="com.pptv.vassdk.ui.activity.pay.PayFailedActivity"
            android:screenOrientation="behind"
            android:theme="@android:style/Theme.Translucent.NoTitleBar.Fullscreen" />
        <activity
            android:name="com.pptv.vassdk.ui.activity.pay.PaySuccessActivity"
            android:screenOrientation="behind"
            android:theme="@android:style/Theme.Translucent.NoTitleBar.Fullscreen" />
        <activity
            android:name="com.pptv.vassdk.ui.activity.pay.PayRsultWaitActivity"
            android:theme="@android:style/Theme.Translucent.NoTitleBar.Fullscreen" />
        <activity
            android:name="com.pptv.vassdk.ui.activity.pay.PayJunEnterActivity"
            android:screenOrientation="behind"
            android:theme="@android:style/Theme.Translucent.NoTitleBar.Fullscreen" />
        <activity
            android:name="com.pptv.vassdk.ui.activity.pay.PayMo9DetailActivity"
            android:screenOrientation="behind"
            android:configChanges="orientation|keyboardHidden"
            android:theme="@android:style/Theme.Translucent.NoTitleBar.Fullscreen" />
        <activity
            android:name="com.pptv.vassdk.ui.activity.pay.YiBaoPayActivity"
            android:screenOrientation="behind"
            android:configChanges="orientation|keyboard|keyboardHidden"
            android:theme="@android:style/Theme.Translucent.NoTitleBar.Fullscreen" />
        <activity
            android:name="com.pptv.vassdk.ui.activity.pay.SzfPayActivity"
            android:screenOrientation="behind"
            android:configChanges="orientation|keyboard|keyboardHidden"
            android:theme="@android:style/Theme.Translucent.NoTitleBar.Fullscreen" />
        <activity
            android:name="com.pptv.vassdk.ui.activity.pay.SftPayActivity"
            android:screenOrientation="behind"
            android:theme="@android:style/Theme.Translucent.NoTitleBar.Fullscreen" />
        <activity
            android:name="com.pptv.vassdk.ui.activity.pay.PayChannelActivity"
            android:screenOrientation="behind"
            android:configChanges="orientation|keyboard|keyboardHidden"
            android:theme="@android:style/Theme.Translucent.NoTitleBar.Fullscreen" />
        <activity
            android:name="com.pptv.vassdk.ui.activity.pay.PayAmountActivity"
            android:screenOrientation="behind"
            android:configChanges="orientation|keyboard|keyboardHidden"
            android:theme="@android:style/Theme.Translucent.NoTitleBar.Fullscreen" />
        <activity
            android:name="com.pptv.vassdk.ui.activity.pay.CashCouponActivity"
            android:screenOrientation="behind"
            android:theme="@android:style/Theme.Translucent.NoTitleBar.Fullscreen" />
        <activity
            android:name="com.pptv.vassdk.ui.activity.welcome.FeedBackActivity"
            android:screenOrientation="behind"
            android:configChanges="orientation|keyboard|keyboardHidden"
            android:theme="@android:style/Theme.Translucent.NoTitleBar.Fullscreen" />
        <activity
            android:name="com.pptv.vassdk.ui.activity.welcome.GCoinChargeActivity"
            android:screenOrientation="behind"
            android:configChanges="keyboardHidden|orientation|screenSize"
            android:theme="@android:style/Theme.Translucent.NoTitleBar.Fullscreen" />
        <activity
            android:name="com.pptv.vassdk.ui.activity.welcome.GCoinChargeChannelChoiceActivity"
            android:screenOrientation="behind"
            android:configChanges="keyboardHidden|orientation|screenSize"
            android:theme="@android:style/Theme.Translucent.NoTitleBar.Fullscreen" />
        <activity
            android:name="com.pptv.vassdk.ui.activity.pay.PayFixAmountActivity"
            android:screenOrientation="behind"
            android:configChanges="keyboardHidden|orientation|screenSize"
            android:theme="@android:style/Theme.Translucent.NoTitleBar.Fullscreen" />
        <activity
            android:name="com.pptv.vassdk.ui.activity.pay.PayGActivity"
            android:screenOrientation="behind"
            android:theme="@android:style/Theme.Translucent.NoTitleBar.Fullscreen" />
        <activity
            android:name="com.pptv.vassdk.ui.activity.pay.PayGInputActivity"
            android:screenOrientation="behind"
            android:theme="@android:style/Theme.Translucent.NoTitleBar.Fullscreen" />
        <activity
            android:name="com.pptv.vassdk.ui.activity.pay.PayChooseAmountActivity"
            android:configChanges="keyboardHidden|orientation|screenSize"
            android:theme="@android:style/Theme.Translucent.NoTitleBar.Fullscreen" />
        <activity
            android:name="com.pptv.vassdk.ui.activity.login.function.WebViewActivity"
            android:configChanges="orientation|keyboard|keyboardHidden|screenSize"
            android:screenOrientation="portrait"
            android:theme="@android:style/Theme.Translucent.NoTitleBar.Fullscreen" />
        <activity
            android:name="com.pptv.vassdk.ui.activity.welcome.FeedBackWebView"
            android:configChanges="orientation|keyboard|keyboardHidden|screenSize"
            android:screenOrientation="portrait"
            android:theme="@android:style/Theme.NoTitleBar"
            android:windowSoftInputMode="stateHidden|adjustResize" />
        <activity
            android:name="com.pptv.vassdk.ui.activity.pay.PayCardInputActivity"
            android:screenOrientation="behind"
            android:theme="@android:style/Theme.Translucent.NoTitleBar.Fullscreen" />
        <activity
            android:name="com.pptv.vassdk.ui.activity.pay.PayFixedAmountChannelsActivity"
            android:screenOrientation="behind"
            android:configChanges="orientation|keyboardHidden"
            android:theme="@android:style/Theme.Translucent.NoTitleBar.Fullscreen" />
        <activity
            android:name="com.pptv.vassdk.ui.activity.pay.PayNormalChoseAmountActivity"
            android:screenOrientation="behind"
            android:theme="@android:style/Theme.Translucent.NoTitleBar.Fullscreen" />
        <activity
            android:name="com.pptv.vassdk.ui.activity.welcome.ShowBannerActivity"
            android:screenOrientation="behind"
            android:theme="@android:style/Theme.Translucent.NoTitleBar.Fullscreen" />
        <activity
            android:name="com.ipaynow.wechatpay.plugin.inner_plugin.wechat_plugin.activity.WeChatNotifyActivity"
            android:configChanges="orientation|keyboardHidden|keyboard|smallestScreenSize|locale|screenLayout"
            android:screenOrientation="portrait"
            android:theme="@android:style/Theme.Translucent" />
        <activity
            android:name="com.unionpay.uppay.PayActivity"
            android:configChanges="orientation|keyboardHidden"
            android:excludeFromRecents="true"
            android:screenOrientation="portrait"
            android:windowSoftInputMode="adjustResize" />
        <activity
            android:name="com.umpay.quickpay.UmpayActivity"
            android:configChanges="orientation|keyboard|keyboardHidden"
            android:screenOrientation="portrait"
            android:theme="@style/ump_translucent"
            android:windowSoftInputMode="stateHidden|adjustResize" />
        <activity
            android:name="com.alipay.sdk.app.H5PayActivity"
            android:configChanges="orientation|keyboardHidden|navigation|screenSize"
            android:exported="false"
            android:screenOrientation="behind"
            android:windowSoftInputMode="adjustResize|stateHidden" />   
	</applicationConfig>

</manifest>